octopin-0.1.4.dist-info/METADATA
octopin-0.1.4.dist-info/WHEEL
octopin-0.1.4.dist-info/entry_points.txt
octopin-0.1.4.dist-info/licenses/LICENSE
octopin/__init__.py
octopin/__main__.py
octopin/_version.py
octopin/actions.py
octopin/cli.py
octopin/dependencies.py
octopin/github.py
octopin/log.py
octopin/pin.py
octopin/py.typed
octopin/workflow_file.py
octopin-0.1.4.dist-info/RECORD
