Metadata-Version: 2.1
Name: octopin
Version: 0.1.4
Summary: Pin used actions and analyse transitive dependencies of GitHub workflows / actions
Author-Email: Thomas Neidhart <thomas.neidhart@eclipse-foundation.org>
License: EPL-2.0
Classifier: Intended Audience :: Developers
Classifier: Operating System :: OS Independent
Classifier: Programming Language :: Python :: 3
Classifier: Programming Language :: Python
Classifier: Topic :: Security
Classifier: Topic :: Software Development
Classifier: Typing :: Typed
Classifier: Development Status :: 4 - Beta
Classifier: Intended Audience :: Developers
Classifier: Programming Language :: Python :: 3 :: Only
Classifier: Programming Language :: Python :: 3.11
Classifier: Programming Language :: Python :: 3.12
Classifier: Programming Language :: Python :: 3.13
Classifier: License :: OSI Approved :: Eclipse Public License 2.0 (EPL-2.0)
Project-URL: Homepage, https://github.com/eclipse-csi/octopin
Project-URL: Documentation, https://octopin.readthedocs.org
Project-URL: Repository, https://github.com/eclipse-csi/octopin
Project-URL: Issues, https://github.com/eclipse-csi/octopin/issues
Project-URL: Changelog, https://octopin.readthedocs.org/release-notes/
Requires-Python: >=3.11
Requires-Dist: typer>=0.15
Requires-Dist: PyYAML>=6.0
Requires-Dist: semver>=3.0
Requires-Dist: aiohttp>=3.9
Requires-Dist: aiohttp-client-cache>=0.10
Requires-Dist: aiosqlite>=0.19
Requires-Dist: platformdirs>=4
